setup.py
test/__init__.py
test/test_threads.py
test/database/__init__.py
test/database/database.py
test/spiders/__init__.py
test/spiders/spider.py
threads_creator/__init__.py
threads_creator/config.py
threads_creator/entry.py
threads_creator.egg-info/PKG-INFO
threads_creator.egg-info/SOURCES.txt
threads_creator.egg-info/dependency_links.txt
threads_creator.egg-info/not-zip-safe
threads_creator.egg-info/top_level.txt
threads_creator/threads/__init__.py
threads_creator/threads/branch_thread.py
threads_creator/threads/main_thread.py
threads_creator/utils/__init__.py
threads_creator/utils/const_value.py
threads_creator/utils/message.py